streamloom/__init__.py
StreamLoom-0.1.2.dist-info/LICENSE
StreamLoom-0.1.2.dist-info/METADATA
StreamLoom-0.1.2.dist-info/WHEEL
StreamLoom-0.1.2.dist-info/top_level.txt
StreamLoom-0.1.2.dist-info/RECORD
