Metadata-Version: 2.1
Name: StreamLoom
Version: 0.1.2
Summary: A modular and extensible Python framework for building, managing, and executing pipelines.
Home-page: https://github.com/creativesands/streamloom
Author: Sandeep S Kumar
Author-email: sanygeek@gmail.com
Classifier: Programming Language :: Python :: 3
Classifier: License :: OSI Approved :: MIT License
Classifier: Operating System :: OS Independent
License-File: LICENSE
